sphinxcontrib/twine/__init__.py
sphinxcontrib/twine/storyformats.json
sphinxcontrib/twine/storyformats.py
sphinxcontrib/twine/twine.py
sphinxcontrib/twine/twine2story.html
sphinxcontrib_twine-0.3.2.dist-info/licenses/LICENSE
sphinxcontrib_twine-0.3.2.dist-info/METADATA
sphinxcontrib_twine-0.3.2.dist-info/WHEEL
sphinxcontrib_twine-0.3.2.dist-info/top_level.txt
sphinxcontrib_twine-0.3.2.dist-info/RECORD
