Metadata-Version: 2.4
Name: sphinxcontrib-twine
Version: 0.3.2
Summary: Add some interactive stories in your Sphinx docs
Author-email: Xing Ji <me@xingji.me>
License-Expression: MIT
Project-URL: Homepage, https://sphinxcontrib-twine.readthedocs.io
Project-URL: Repository, https://github.com/jixingcn/sphinxcontrib-twine
Project-URL: Changelog, https://github.com/jixingcn/sphinxcontrib-twine/blob/main/CHANGELOG.rst
Project-URL: Issues, https://github.com/jixingcn/sphinxcontrib-twine/issues
Keywords: sphinx,twinery,twine2,twee3,chapbook,story
Classifier: Development Status :: 3 - Alpha
Classifier: Environment :: Web Environment
Classifier: Framework :: Sphinx
Classifier: Framework :: Sphinx :: Extension
Classifier: Operating System :: OS Independent
Classifier: Programming Language :: Python :: 3
Classifier: Topic :: Documentation
Classifier: Topic :: Utilities
Requires-Python: >=3.7
License-File: LICENSE
Requires-Dist: sphinx
Requires-Dist: pytwee
Requires-Dist: Jinja2
Dynamic: license-file
